ModelPK/__init__.py
ModelPK/extractPKparam.py
ModelPK/simulatePK.py
ModelPK/test_ModelPK.py
ModelPK-0.4.dist-info/LICENSE
ModelPK-0.4.dist-info/METADATA
ModelPK-0.4.dist-info/WHEEL
ModelPK-0.4.dist-info/top_level.txt
ModelPK-0.4.dist-info/RECORD
