Metadata-Version: 2.1
Name: ModelPK
Version: 0.4
Summary: A package for pharmacokinetic modeling
Author-email: Jia Liang <jyliang@uw.edu>
License: MIT License
Project-URL: ModelPK, https://github.com/jyliang27/ModelPK
Classifier: Programming Language :: Python :: 3
Classifier: License :: OSI Approved :: MIT License
Classifier: Operating System :: OS Independent
Requires-Python: >=3.7
License-File: LICENSE
Requires-Dist: pandas
Requires-Dist: numpy
Requires-Dist: tellurium
Requires-Dist: scikit-learn
